tutti_product_tagger/__init__.py
tutti_product_tagger/tagger.py
tutti_product_tagger-1.1.5.dist-info/LICENSE
tutti_product_tagger-1.1.5.dist-info/METADATA
tutti_product_tagger-1.1.5.dist-info/WHEEL
tutti_product_tagger-1.1.5.dist-info/top_level.txt
tutti_product_tagger-1.1.5.dist-info/zip-safe
tutti_product_tagger-1.1.5.dist-info/RECORD
